canari/__init__.py
canari/common.py
canari/data_process.py
canari/data_struct.py
canari/data_visualization.py
canari/model.py
canari/model_assemble.py
canari/optimizer.py
canari/skf.py
canari/component/__init__.py
canari/component/autoregression_component.py
canari/component/base_component.py
canari/component/baseline_component.py
canari/component/bounded_autoregression_component.py
canari/component/exponential_component.py
canari/component/lstm_component.py
canari/component/periodic_component.py
canari/component/white_noise_component.py
pycanari-0.2.4.dist-info/licenses/LICENSE
pycanari-0.2.4.dist-info/METADATA
pycanari-0.2.4.dist-info/WHEEL
pycanari-0.2.4.dist-info/top_level.txt
pycanari-0.2.4.dist-info/RECORD
